discord/ext/flags/__init__.py
discord/ext/flags/_command.py
discord/ext/flags/_parser.py
alt_discord_flags-0.0.5.dist-info/LICENSE.md
alt_discord_flags-0.0.5.dist-info/METADATA
alt_discord_flags-0.0.5.dist-info/WHEEL
alt_discord_flags-0.0.5.dist-info/top_level.txt
alt_discord_flags-0.0.5.dist-info/RECORD
